odoo/addons/account_ecotax_sale_tax/README.rst
odoo/addons/account_ecotax_sale_tax/__init__.py
odoo/addons/account_ecotax_sale_tax/__manifest__.py
odoo/addons/account_ecotax_sale_tax/i18n/account_ecotax_sale_tax.pot
odoo/addons/account_ecotax_sale_tax/i18n/it.po
odoo/addons/account_ecotax_sale_tax/models/__init__.py
odoo/addons/account_ecotax_sale_tax/models/sale_order_line.py
odoo/addons/account_ecotax_sale_tax/readme/CONTRIBUTORS.rst
odoo/addons/account_ecotax_sale_tax/readme/DESCRIPTION.rst
odoo/addons/account_ecotax_sale_tax/static/description/icon.png
odoo/addons/account_ecotax_sale_tax/static/description/index.html
odoo/addons/account_ecotax_sale_tax/tests/__init__.py
odoo/addons/account_ecotax_sale_tax/tests/test_sale_ecotax.py
odoo/addons/account_ecotax_sale_tax/views/sale_view.xml
odoo_addon_account_ecotax_sale_tax-16.0.2.0.1.dist-info/METADATA
odoo_addon_account_ecotax_sale_tax-16.0.2.0.1.dist-info/WHEEL
odoo_addon_account_ecotax_sale_tax-16.0.2.0.1.dist-info/top_level.txt
odoo_addon_account_ecotax_sale_tax-16.0.2.0.1.dist-info/RECORD
